main.py
nlcopt-0.0.1.dist-info/METADATA
nlcopt-0.0.1.dist-info/WHEEL
nlcopt-0.0.1.dist-info/top_level.txt
nlcopt-0.0.1.dist-info/RECORD
