Metadata-Version: 2.4
Name: nlcopt
Version: 0.0.1
Summary: Non-Linear Constraint Optimization Package
Requires-Python: >=3.9
